{"rating": 4.6, "name": "Statue of Liberty National Monument", "timings": [{"close": {"day": 0, "time": "1600"}, "open": {"day": 0, "time": "0830"}}, {"close": {"day": 1, "time": "1600"}, "open": {"day": 1, "time": "0830"}}, {"close": {"day": 2, "time": "1600"}, "open": {"day": 2, "time": "0830"}}, {"close": {"day": 3, "time": "1600"}, "open": {"day": 3, "time": "0830"}}, {"close": {"day": 4, "time": "1600"}, "open": {"day": 4, "time": "0830"}}, {"close": {"day": 5, "time": "1600"}, "open": {"day": 5, "time": "0830"}}, {"close": {"day": 6, "time": "1600"}, "open": {"day": 6, "time": "0830"}}], "northeast_corner": {"lat": 40.71823, "lng": -73.99872490000001}, "lat": 40.6892494, "southwest_corner": {"lat": 40.6795892, "lng": -74.05975889999998}, "lng": -74.04450039999999, "types": ["park", "point_of_interest", "establishment"]}